Metadata-Version: 1.1
Name: colorgnomehat
Version: 0.0.1
Summary: a python program that will generate colors for text and variables
Home-page: UNKNOWN
Author: Rigved Aneesh
Author-email: rigved.bob@gmail.com
License: UNKNOWN
Platform: UNKNOWN
Classifier: Development Status :: 3 - Alpha
Classifier: Intended Audience :: Education
Classifier: Programming Language :: Python :: 3
